formatter/__init__.py
formatter/__main__.py
formatter/base_formatter.py
formatter/exceptions.py
formatter/deepspeech/__init__.py
formatter/deepspeech/deepspeech.py
formatter/deepspeech/item.py
ML_Formatter-1.0.1.dist-info/METADATA
ML_Formatter-1.0.1.dist-info/WHEEL
ML_Formatter-1.0.1.dist-info/top_level.txt
ML_Formatter-1.0.1.dist-info/RECORD
