Metadata-Version: 2.1
Name: ML-Formatter
Version: 1.0.1
Summary: An easy to use package for parsing media and transforming it for your Machine Learning projects.
Home-page: https://github.com/Skelmis/ML-Formatter
Author: Skelmis
Author-email: ethan@koldfusion.xyz
License: UNKNOWN
Platform: UNKNOWN
Classifier: Programming Language :: Python :: 3
Classifier: Operating System :: OS Independent
Classifier: Development Status :: 5 - Production/Stable
Requires-Python: >=3.6
Requires-Dist: attrs
